LICENSE
README.md
setup.py
gcardella_fib_py/__init__.py
gcardella_fib_py.egg-info/PKG-INFO
gcardella_fib_py.egg-info/SOURCES.txt
gcardella_fib_py.egg-info/dependency_links.txt
gcardella_fib_py.egg-info/entry_points.txt
gcardella_fib_py.egg-info/top_level.txt
gcardella_fib_py/cmd/__init__.py
gcardella_fib_py/cmd/fib_numb.py
gcardella_fib_py/fib_calcs/__init__.py
gcardella_fib_py/fib_calcs/fib_number.py
gcardella_fib_py/fib_calcs/fib_numbers.py