Metadata-Version: 2.1
Name: gcardella-fib-py
Version: 0.0.1
Summary: Calculates a Fibonacci number
Home-page: https://github.com/jc-development/fib-py
Author: Joe C
Author-email: 
Classifier: Development Status :: 4 - Beta
Classifier: Programming Language :: Python :: 3
Classifier: Operating System :: OS Independent
Requires-Python: >=3
License-File: LICENSE
